README.md
setup.py
InceptionFlow/__init__.py
InceptionFlow.egg-info/PKG-INFO
InceptionFlow.egg-info/SOURCES.txt
InceptionFlow.egg-info/dependency_links.txt
InceptionFlow.egg-info/requires.txt
InceptionFlow.egg-info/top_level.txt