Metadata-Version: 1.0
Name: InceptionFlow
Version: 0.1.3
Summary: Object & Facial Recognition With IoT Communication. Using Tensorflow Inception V3 & TechBubble IoT JumpWay
Home-page: https://github.com/AdamMiltonBarker/InceptionFlow
Author: Adam Milton-Barker
Author-email: adammiltonbarker@gmail.com
License: UNKNOWN
Platform: UNKNOWN
